<config>
    <frameworks>
        <framework>GoogleSignIn</framework>

        <framework>AppAuth</framework>
        <framework>GTMAppAuth</framework>
        <framework>GTMSessionFetcher</framework>
        <framework>LocalAuthentication</framework>
        <framework>SafariServices</framework>
        <framework>AuthenticationServices</framework>
        <framework>SystemConfiguration</framework>
        <framework>CoreText</framework>
        <framework>CoreGraphics</framework>
    </frameworks>
</config>